omop2owl_vocab/__init__.py
omop2owl_vocab/__main__.py
omop2owl_vocab/omop2owl_vocab.py
omop2owl_vocab/prefixes.csv
omop2owl_vocab/robot.jar
omop2owl_vocab-1.3.5.dist-info/LICENSE
omop2owl_vocab-1.3.5.dist-info/METADATA
omop2owl_vocab-1.3.5.dist-info/WHEEL
omop2owl_vocab-1.3.5.dist-info/entry_points.txt
omop2owl_vocab-1.3.5.dist-info/top_level.txt
omop2owl_vocab-1.3.5.dist-info/RECORD
