Metadata-Version: 2.1
Name: omop2owl-vocab
Version: 1.3.5
Summary: Convert OMOP vocab into OWL and SemanticSQL.
Home-page: https://github.com/HOT-Ecosystem/omop2owl-vocab/
Author: Joe Flack
Author-email: jflack@jhu.edu
Classifier: License :: OSI Approved :: MIT License
Classifier: Programming Language :: Python
Classifier: Programming Language :: Python :: 3
Classifier: Programming Language :: Python :: 3.9
Classifier: Programming Language :: Python :: 3.10
Classifier: Programming Language :: Python :: Implementation :: CPython
Classifier: Programming Language :: Python :: Implementation :: PyPy
Requires-Python: >=3.9.0
License-File: LICENSE
Requires-Dist: oaklib >=0.5.20
Requires-Dist: pandas
